pyinat/__init__.py
pyinaturalist/__init__.py
pyinaturalist/auth.py
pyinaturalist/client.py
pyinaturalist/constants.py
pyinaturalist/converters.py
pyinaturalist/exceptions.py
pyinaturalist/formatters.py
pyinaturalist/node_api.py
pyinaturalist/paginator.py
pyinaturalist/py.typed
pyinaturalist/request_params.py
pyinaturalist/rest_api.py
pyinaturalist/session.py
pyinaturalist/controllers/__init__.py
pyinaturalist/controllers/annotation_controller.py
pyinaturalist/controllers/base_controller.py
pyinaturalist/controllers/identification_controller.py
pyinaturalist/controllers/observation_controller.py
pyinaturalist/controllers/place_controller.py
pyinaturalist/controllers/project_controller.py
pyinaturalist/controllers/search_controller.py
pyinaturalist/controllers/taxon_controller.py
pyinaturalist/controllers/user_controller.py
pyinaturalist/docs/__init__.py
pyinaturalist/docs/docstrings.py
pyinaturalist/docs/emoji.py
pyinaturalist/docs/model_docs.py
pyinaturalist/docs/signatures.py
pyinaturalist/docs/templates.py
pyinaturalist/models/__init__.py
pyinaturalist/models/base.py
pyinaturalist/models/checklist.py
pyinaturalist/models/conservation_status.py
pyinaturalist/models/controlled_term.py
pyinaturalist/models/identification.py
pyinaturalist/models/lazy_property.py
pyinaturalist/models/media.py
pyinaturalist/models/message.py
pyinaturalist/models/observation.py
pyinaturalist/models/observation_field.py
pyinaturalist/models/place.py
pyinaturalist/models/project.py
pyinaturalist/models/search.py
pyinaturalist/models/taxon.py
pyinaturalist/models/user.py
pyinaturalist/v0/__init__.py
pyinaturalist/v0/observation_fields.py
pyinaturalist/v0/observations.py
pyinaturalist/v1/__init__.py
pyinaturalist/v1/controlled_terms.py
pyinaturalist/v1/identifications.py
pyinaturalist/v1/messages.py
pyinaturalist/v1/observation_fields.py
pyinaturalist/v1/observations.py
pyinaturalist/v1/places.py
pyinaturalist/v1/posts.py
pyinaturalist/v1/projects.py
pyinaturalist/v1/search.py
pyinaturalist-0.21.0.dist-info/METADATA
pyinaturalist-0.21.0.dist-info/WHEEL
pyinaturalist-0.21.0.dist-info/licenses/LICENSE
pyinaturalist-0.21.0.dist-info/RECORD
