Metadata-Version: 2.4
Name: pyinaturalist
Version: 0.21.0
Summary: iNaturalist API client for python
Project-URL: homepage, https://github.com/pyinat/pyinaturalist
Project-URL: repository, https://github.com/pyinat/pyinaturalist
Project-URL: documentation, https://pyinaturalist.readthedocs.io
Author: Jordan Cook
License-Expression: MIT
License-File: LICENSE
Keywords: api,api-client,biodiversity,citizen-science,community-science,conservation,data-model,inaturalist,requests
Classifier: Development Status :: 4 - Beta
Classifier: Intended Audience :: Developers
Classifier: Intended Audience :: Education
Classifier: Intended Audience :: Science/Research
Classifier: Programming Language :: Python :: 3
Classifier: Programming Language :: Python :: 3.8
Classifier: Programming Language :: Python :: 3.9
Classifier: Programming Language :: Python :: 3.10
Classifier: Programming Language :: Python :: 3.11
Classifier: Programming Language :: Python :: 3.12
Classifier: Programming Language :: Python :: 3.13
Classifier: Programming Language :: Python :: 3.14
Classifier: Topic :: Software Development :: Libraries :: Python Modules
Classifier: Typing :: Typed
Requires-Python: >=3.8
Requires-Dist: attrs>=21.2
Requires-Dist: keyring>=22.3
Requires-Dist: platformdirs>=2.6
Requires-Dist: python-dateutil>=2.0
Requires-Dist: requests-cache>=1.2
Requires-Dist: requests-ratelimiter>=0.5.1
Requires-Dist: requests>=2.25
Requires-Dist: rich>=10.9
Provides-Extra: all
Requires-Dist: filelock>2.0; extra == 'all'
Requires-Dist: ujson>5.0; extra == 'all'
